{
  "layout": {
    "А": [1.0, "lm+pm"],
    "Б": [3.0, "ly+pm"],
    "В": [2.0, "lb+pm"],
    "Г": [2.0, "ly+pm"],
    "Д": [1.0, "ls+lm"],
    "Е": [2.0, "ls+ lm "],
    "Ё": [3.0, "ly+ lm "],
    "Ж": [2.0, "ly+lm"],
    "З": [2.0, "lm+ pm "],
    "И": [2.0, "ps+ pm "],
    "Й": [1.0, "py+ pm "],
    "К": [1.0, "ps+pm "],
    "Л": [1.0, "pb+pm "],
    "М": [2.0, "py+ pm "],
    "Н": [3.0, "py+pm "],
    "О": [2.0, "pb+pm "],
    "П": [2.0, "pm+lm "],
    "Р": [2.0, "ly+lm "],
    "С": [1.0, "lb+lm "],
    "Т": [3.0, "ly+lm "],
    "У": [2.0, "py+pm "],
    "Ф": [1.0, "ly+pm "],
    "Х": [2.0, "py+pm "],
    "Ц": [2.0, "ls+lm "],
    "Ч": [4.0, "pm+lm "],
    "Ш": [3.0, "pm+lm "],
    "Щ": [4.0, "pm+lm "],
    "Ъ": [3.0, "py+pm "],
    "Ы": [3.0, "py+pm "],
    "Ь": [3.0, "lb+lm "],
    "Э": [5.0, "pm+lm "],
    "Ю": [4.0, "lm+pm "],
    "Я": [2.0, "lm+pm "],
    "а": [0.0, "lm "],
    "б": [2.0, "ly"],
    "в": [1.0, "lb "],
    "г": [1.0, "ly "],
    "д": [0.0, "ls"],
    "е": [1.0, "ls "],
    "ё": [3.0, "ls "],
    "ж": [1.0, "ly "],
    "з": [1.0, "lm "],
    "и": [1.0, "ps "],
    "й": [0.0, "py "],
    "к": [0.0, "ps "],
    "л": [0.0, "pb "],
    "м": [1.0, "py "],
    "н": [2.0, "py "],
    "о": [1.0, "pb "],
    "п": [1.0, "pm "],
    "р": [1.0, "ly "],
    "с": [0.0, "lb "],
    "т": [2.0, "ly "],
    "у": [1.0, "py "],
    "ф": [0.0, "ly "],
    "х": [1.0, "py "],
    "ц": [1.0, "ls "],
    "ч": [3.0, "pm "],
    "ш": [2.0, "pm "],
    "щ": [3.0, "pm "],
    "ъ": [4.0, "ly "],
    "ы": [2.0, "py "],
    "ь": [2.0, "lb "],
    "э": [4.0, "pm "],
    "ю": [3.0, "lm "],
    "я": [1.0, "lm "],
    ".": [1.0, "pb "],
    ",": [1.0, "ps"],
    "?": [2.0, "pm+lm "],
    ":": [1.0, "pm+lm "],
    "!": [3.0, "lm +pm"],
    ";": [0.0, "pm "],
    "-": [4.0, "pm+lm"],
    "*": [3.0, "ls+pm "],
    "(": [3.0, "pb+lm "],
    ")": [3.0, "pm+lm "]
},
  "metadata": {
    "name": "rusphon Layout",
    "description": "Standard rusphon keyboard layout with error weights",
    "created": "2025-10-18",
    "version": "1.0"
  }
}